odoo/addons/hr_emergency_contact/README.rst
odoo/addons/hr_emergency_contact/__init__.py
odoo/addons/hr_emergency_contact/__manifest__.py
odoo/addons/hr_emergency_contact/i18n/ar.po
odoo/addons/hr_emergency_contact/i18n/cs_CZ.po
odoo/addons/hr_emergency_contact/i18n/de.po
odoo/addons/hr_emergency_contact/i18n/es.po
odoo/addons/hr_emergency_contact/i18n/fi.po
odoo/addons/hr_emergency_contact/i18n/fr.po
odoo/addons/hr_emergency_contact/i18n/hr.po
odoo/addons/hr_emergency_contact/i18n/hr_HR.po
odoo/addons/hr_emergency_contact/i18n/hr_emergency_contact.pot
odoo/addons/hr_emergency_contact/i18n/it.po
odoo/addons/hr_emergency_contact/i18n/lt.po
odoo/addons/hr_emergency_contact/i18n/nl_NL.po
odoo/addons/hr_emergency_contact/i18n/pt_BR.po
odoo/addons/hr_emergency_contact/i18n/ro.po
odoo/addons/hr_emergency_contact/i18n/sl.po
odoo/addons/hr_emergency_contact/models/__init__.py
odoo/addons/hr_emergency_contact/models/hr_employee.py
odoo/addons/hr_emergency_contact/static/description/icon.png
odoo/addons/hr_emergency_contact/views/hr_employee_views.xml
odoo11_addon_hr_emergency_contact-11.0.1.0.0.99.dev3.dist-info/METADATA
odoo11_addon_hr_emergency_contact-11.0.1.0.0.99.dev3.dist-info/RECORD
odoo11_addon_hr_emergency_contact-11.0.1.0.0.99.dev3.dist-info/WHEEL
odoo11_addon_hr_emergency_contact-11.0.1.0.0.99.dev3.dist-info/top_level.txt
